typedattr/__init__.py
typedattr/_typedattr.py
typedattr/const.py
typedattr/typext.py
typedattr/utils/__init__.py
typedattr/utils/caching.py
typedattr/utils/debugging.py
typedattr/utils/dtime.py
typedattr/utils/files.py
typedattr/utils/import_from_source.py
typedattr/utils/log.py
typedattr/utils/objects.py
typedattr/utils/system.py
typedattr-0.2.6.dist-info/LICENSE
typedattr-0.2.6.dist-info/METADATA
typedattr-0.2.6.dist-info/WHEEL
typedattr-0.2.6.dist-info/top_level.txt
typedattr-0.2.6.dist-info/zip-safe
typedattr-0.2.6.dist-info/RECORD
