Metadata-Version: 2.1
Name: typedattr
Version: 0.2.6
Summary: Typed conversion of dictionaries to attrs instances
Author: gingsi
License: Apache-2.0
Project-URL: Project-URL, https://github.com/gingsi/typedattr
Keywords: attrs,typing,dict,attr
Platform: any
Classifier: Development Status :: 3 - Alpha
Classifier: Intended Audience :: Developers
Classifier: License :: OSI Approved :: Apache Software License
Classifier: Natural Language :: English
Classifier: Programming Language :: Python :: 3.7
Classifier: Programming Language :: Python :: 3.8
Classifier: Programming Language :: Python :: 3.9
Classifier: Operating System :: OS Independent
Classifier: Topic :: Software Development :: Version Control :: Git
Requires-Python: >=3.7
License-File: LICENSE
Requires-Dist: attrs
Requires-Dist: numpy
Requires-Dist: joblib
Requires-Dist: importlib-resources
Requires-Dist: loguru
